aissemble_open_inference_protocol_shared/__init__.py
aissemble_open_inference_protocol_shared/aissemble_oip_service.py
aissemble_open_inference_protocol_shared/auth/__init__.py
aissemble_open_inference_protocol_shared/auth/auth_adapter_base.py
aissemble_open_inference_protocol_shared/auth/auth_context.py
aissemble_open_inference_protocol_shared/auth/authzforce_adapter.py
aissemble_open_inference_protocol_shared/auth/default_adapter.py
aissemble_open_inference_protocol_shared/auth/jwt_auth.py
aissemble_open_inference_protocol_shared/auth/xacml3_builder.py
aissemble_open_inference_protocol_shared/codecs/__init__.py
aissemble_open_inference_protocol_shared/codecs/codec.py
aissemble_open_inference_protocol_shared/codecs/numpy.py
aissemble_open_inference_protocol_shared/codecs/registry.py
aissemble_open_inference_protocol_shared/codecs/strategies/__init__.py
aissemble_open_inference_protocol_shared/codecs/strategies/output_processing_strategy.py
aissemble_open_inference_protocol_shared/codecs/string.py
aissemble_open_inference_protocol_shared/codecs/utils.py
aissemble_open_inference_protocol_shared/config/__init__.py
aissemble_open_inference_protocol_shared/config/kserve_args_parser.py
aissemble_open_inference_protocol_shared/config/oip_config.py
aissemble_open_inference_protocol_shared/handlers/__init__.py
aissemble_open_inference_protocol_shared/handlers/dataplane.py
aissemble_open_inference_protocol_shared/handlers/model_handler.py
aissemble_open_inference_protocol_shared/types/__init__.py
aissemble_open_inference_protocol_shared/types/dataplane.py
aissemble_open_inference_protocol_shared-1.1.0.dist-info/METADATA
aissemble_open_inference_protocol_shared-1.1.0.dist-info/WHEEL
aissemble_open_inference_protocol_shared-1.1.0.dist-info/licenses/LICENSE.txt
aissemble_open_inference_protocol_shared-1.1.0.dist-info/RECORD
