Metadata-Version: 2.4
Name: aissemble-open-inference-protocol-shared
Version: 1.1.0
Summary: Shared Utilities for aiSSEMBLE Open Inference Protocol
License-Expression: Apache-2.0
License-File: LICENSE.txt
Author: aiSSEMBLE Solutions Community
Author-email: aissemble@bah.com
Requires-Python: >=3.10,<3.13
Classifier: Programming Language :: Python :: 3
Classifier: Programming Language :: Python :: 3.10
Classifier: Programming Language :: Python :: 3.11
Classifier: Programming Language :: Python :: 3.12
Classifier: License :: Other/Proprietary License
Classifier: Operating System :: OS Independent
Classifier: Intended Audience :: Developers
Requires-Dist: cryptography (>=44.0.1)
Requires-Dist: fastapi[standard] (>=0.116.1)
Requires-Dist: krausening (>=20)
Requires-Dist: numpy (>=1.26.0)
Requires-Dist: pydantic (>=2.11.4,<3.0.0)
Requires-Dist: starlette (>=0.47.2)
Project-URL: Homepage, https://github.com/boozallen/aissemble-open-inference-protocol
